setup.cfg
setup.py
Products/__init__.py
Products.ECLecture.egg-info/PKG-INFO
Products.ECLecture.egg-info/SOURCES.txt
Products.ECLecture.egg-info/dependency_links.txt
Products.ECLecture.egg-info/entry_points.txt
Products.ECLecture.egg-info/namespace_packages.txt
Products.ECLecture.egg-info/not-zip-safe
Products.ECLecture.egg-info/requires.txt
Products.ECLecture.egg-info/top_level.txt
Products/ECLecture/CHANGES.txt
Products/ECLecture/LICENSE.GPL
Products/ECLecture/LICENSE.TXT
Products/ECLecture/README.txt
Products/ECLecture/__init__.py
Products/ECLecture/config.py
Products/ECLecture/configure.zcml
Products/ECLecture/profiles.zcml
Products/ECLecture/refresh.txt
Products/ECLecture/setuphandlers.py
Products/ECLecture/version.txt
Products/ECLecture/content/ECLecture.py
Products/ECLecture/content/TimePeriodField.py
Products/ECLecture/content/__init__.py
Products/ECLecture/content/interfaces.py
Products/ECLecture/content/validators.py
Products/ECLecture/i18n/eduComponents-de.po
Products/ECLecture/i18n/eduComponents.pot
Products/ECLecture/i18n/other.pot
Products/ECLecture/i18n/plone-de.po
Products/ECLecture/i18n/schemas.pot
Products/ECLecture/portlets/__init__.py
Products/ECLecture/portlets/configure.zcml
Products/ECLecture/portlets/portlet.pt
Products/ECLecture/portlets/portlet.py
Products/ECLecture/profiles/default/ECLecture_marker.txt
Products/ECLecture/profiles/default/catalog.xml
Products/ECLecture/profiles/default/cssregistry.xml
Products/ECLecture/profiles/default/factorytool.xml
Products/ECLecture/profiles/default/import_steps.xml
Products/ECLecture/profiles/default/jsregistry.xml
Products/ECLecture/profiles/default/metadata.xml
Products/ECLecture/profiles/default/portlets.xml
Products/ECLecture/profiles/default/skins.xml
Products/ECLecture/profiles/default/types.xml
Products/ECLecture/profiles/default/types/ECLecture.xml
Products/ECLecture/skins/eclecture_images/eclecture.png
Products/ECLecture/skins/eclecture_styles/ecl_styles.css.dtml
Products/ECLecture/skins/eclecture_templates/ecl_participants.cpt
Products/ECLecture/skins/eclecture_templates/ecl_participants.cpt.metadata
Products/ECLecture/skins/eclecture_templates/ecl_participants_export.py
Products/ECLecture/skins/eclecture_templates/ecl_register.cpy
Products/ECLecture/skins/eclecture_templates/ecl_register.cpy.metadata
