Metadata-Version: 1.0
Name: Products.ECLecture
Version: 1.4
Summary: Managing lectures, seminars and other courses.
Home-page: http://plone.org/products/eclecture/
Author: Mario Amelung and Michael Piotrowski
Author-email: mario.amelung@gmx.de and mxp@dynalabs.de
License: GPL
Platform: UNKNOWN
Classifier: Framework :: Plone
Classifier: Framework :: Zope2
Classifier: Programming Language :: Python
Classifier: Topic :: Software Development :: Libraries :: Python Modules
